sbdk/__init__.py
sbdk/context.py
sbdk/exceptions.py
sbdk/formatters.py
sbdk/validators.py
sbdk/cli/__init__.py
sbdk/cli/base.py
sbdk/cli/dbt_utils.py
sbdk/cli/debug.py
sbdk/cli/enhanced_components.py
sbdk/cli/integration_layer.py
sbdk/cli/interactive.py
sbdk/cli/main.py
sbdk/cli/visual_cli_robust.py
sbdk/cli/commands/__init__.py
sbdk/cli/commands/dev.py
sbdk/cli/commands/init.py
sbdk/cli/commands/query.py
sbdk/cli/commands/run.py
sbdk/cli/commands/start.py
sbdk/cli/commands/webhooks.py
sbdk/cli/visual/__init__.py
sbdk/cli/visual/app.py
sbdk/cli/visual/components.py
sbdk/cli/visual/renderer.py
sbdk/core/__init__.py
sbdk/core/config.py
sbdk/core/project.py
sbdk/templates/query.py
sbdk/templates/requirements.txt
sbdk/templates/dbt/dbt_project.yml
sbdk/templates/dbt/models/_sources.yml
sbdk/templates/dbt/models/intermediate/int_user_activity.sql
sbdk/templates/dbt/models/marts/user_metrics.sql
sbdk/templates/dbt/models/staging/stg_events.sql
sbdk/templates/dbt/models/staging/stg_orders.sql
sbdk/templates/dbt/models/staging/stg_users.sql
sbdk/templates/fastapi_server/webhook_listener.py
sbdk/templates/pipelines/events.py
sbdk/templates/pipelines/orders.py
sbdk/templates/pipelines/users.py
sbdk_dev-1.1.2.dist-info/licenses/LICENSE
sbdk_dev-1.1.2.dist-info/METADATA
sbdk_dev-1.1.2.dist-info/WHEEL
sbdk_dev-1.1.2.dist-info/entry_points.txt
sbdk_dev-1.1.2.dist-info/top_level.txt
sbdk_dev-1.1.2.dist-info/RECORD
