Metadata-Version: 2.4
Name: sbdk-dev
Version: 1.1.2
Summary: 🚀 Local-first data pipeline sandbox: DuckDB + dbt + DLT with interactive SQL query - Zero setup, instant analytics
Author-email: "SBDK.dev Team" <hello@sbdk.dev>
Maintainer-email: "SBDK.dev Team" <hello@sbdk.dev>
License: MIT
Project-URL: Homepage, https://sbdk.dev
Project-URL: Documentation, https://docs.sbdk.dev
Project-URL: Repository, https://github.com/sbdk-dev/sbdk
Project-URL: Bug Tracker, https://github.com/sbdk-dev/sbdk/issues
Project-URL: Changelog, https://github.com/sbdk-dev/sbdk/blob/main/CHANGELOG.md
Keywords: data-pipeline,duckdb,dbt,dlt,etl,elt,local-first,data-engineering,analytics,sql,query,cli,sandbox,development,data-science,olap,data-warehouse,pipeline,transformation,database
Classifier: Development Status :: 4 - Beta
Classifier: Environment :: Console
Classifier: Framework :: Pydantic
Classifier: Framework :: Pydantic :: 2
Classifier: Intended Audience :: Developers
Classifier: Intended Audience :: Science/Research
Classifier: Intended Audience :: System Administrators
Classifier: Intended Audience :: Information Technology
Classifier: Intended Audience :: Education
Classifier: License :: OSI Approved :: MIT License
Classifier: Natural Language :: English
Classifier: Operating System :: OS Independent
Classifier: Operating System :: MacOS
Classifier: Operating System :: Microsoft :: Windows
Classifier: Operating System :: POSIX :: Linux
Classifier: Programming Language :: Python :: 3
Classifier: Programming Language :: Python :: 3.9
Classifier: Programming Language :: Python :: 3.10
Classifier: Programming Language :: Python :: 3.11
Classifier: Programming Language :: Python :: 3.12
Classifier: Programming Language :: Python :: 3.13
Classifier: Programming Language :: Python :: 3 :: Only
Classifier: Programming Language :: SQL
Classifier: Topic :: Database
Classifier: Topic :: Database :: Database Engines/Servers
Classifier: Topic :: Software Development
Classifier: Topic :: Software Development :: Libraries
Classifier: Topic :: Software Development :: Libraries :: Python Modules
Classifier: Topic :: Software Development :: Testing
Classifier: Topic :: Scientific/Engineering
Classifier: Topic :: Scientific/Engineering :: Information Analysis
Classifier: Topic :: Utilities
Classifier: Typing :: Typed
Requires-Python: >=3.9
License-File: LICENSE
Requires-Dist: typer>=0.12.0
Requires-Dist: rich>=13.7.0
Requires-Dist: fastapi>=0.104.0
Requires-Dist: uvicorn[standard]>=0.24.0
Requires-Dist: duckdb>=0.9.0
Requires-Dist: pandas>=2.1.0
Requires-Dist: faker>=20.1.0
Requires-Dist: dbt-core>=1.7.0
Requires-Dist: dbt-duckdb>=1.7.0
Requires-Dist: dynaconf>=3.2.0
Requires-Dist: httpx>=0.25.0
Requires-Dist: pydantic>=2.5.0
Requires-Dist: watchdog>=3.0.0
Requires-Dist: dlt[duckdb]>=0.4.0
Requires-Dist: psutil>=5.9.0
Requires-Dist: pyyaml>=6.0.0
Requires-Dist: deepdiff>=8.6.1
Provides-Extra: dev
Requires-Dist: pytest>=7.4.0; extra == "dev"
Requires-Dist: pytest-cov>=4.1.0; extra == "dev"
Requires-Dist: pytest-asyncio>=0.21.0; extra == "dev"
Requires-Dist: black>=23.0.0; extra == "dev"
Requires-Dist: ruff>=0.1.0; extra == "dev"
Requires-Dist: mypy>=1.7.0; extra == "dev"
Requires-Dist: pre-commit>=3.5.0; extra == "dev"
Provides-Extra: docs
Requires-Dist: mkdocs>=1.5.0; extra == "docs"
Requires-Dist: mkdocs-material>=9.4.0; extra == "docs"
Requires-Dist: mkdocstrings[python]>=0.24.0; extra == "docs"
Provides-Extra: test
Requires-Dist: pytest>=7.4.0; extra == "test"
Requires-Dist: pytest-cov>=4.1.0; extra == "test"
Requires-Dist: pytest-asyncio>=0.21.0; extra == "test"
Requires-Dist: coverage>=7.3.0; extra == "test"
Dynamic: license-file
